automata_toolkit/__init__.py
automata_toolkit/consts.py
automata_toolkit/dfa_to_efficient_dfa.py
automata_toolkit/dfa_to_regex.py
automata_toolkit/nfa_to_dfa.py
automata_toolkit/regex_to_nfa.py
automata_toolkit/regex_to_postfix.py
automata_toolkit/visual_utils.py
automata_toolkit-1.0.2.dist-info/LICENSE.md
automata_toolkit-1.0.2.dist-info/METADATA
automata_toolkit-1.0.2.dist-info/WHEEL
automata_toolkit-1.0.2.dist-info/top_level.txt
automata_toolkit-1.0.2.dist-info/RECORD
