Metadata-Version: 2.1
Name: automata-toolkit
Version: 1.0.2
Summary: A tiny library which contains tools to convert, minimize and visualize Regular Expressions, NFA and DFA.
Home-page: https://github.com/b30wulffz/automata-toolkit
Author: Shlok Pandey
Author-email: shlokpandey123@gmail.com
License: MIT
Keywords: automata,visualizer,nfa,dfa,regular expression
Platform: UNKNOWN
Classifier: License :: OSI Approved :: MIT License
Classifier: Programming Language :: Python :: 3
Classifier: Programming Language :: Python :: 3.7
